geko/__init__.py
geko/config.py
geko/fitting.py
geko/grism.py
geko/models.py
geko/plotting.py
geko/postprocess.py
geko/preprocess.py
geko/utils.py
astro_geko-1.0.0.dist-info/METADATA
astro_geko-1.0.0.dist-info/WHEEL
astro_geko-1.0.0.dist-info/top_level.txt
astro_geko-1.0.0.dist-info/RECORD
