Metadata-Version: 2.4
Name: astro-geko
Version: 1.0.0
Summary: Geko: the Grism Emission-line Kinematics tOol
Author-email: "A. Lola Danhaive" <angelicalola.danhaive@gmail.com>
License: MIT
Project-URL: Homepage, https://github.com/angelicalola-danhaive/geko
Project-URL: Documentation, https://astro-geko.readthedocs.io
Project-URL: Repository, https://github.com/angelicalola-danhaive/geko
Keywords: astronomy,jwst,grism,spectroscopy,kinematics,bayesian,mcmc
Classifier: Development Status :: 4 - Beta
Classifier: Intended Audience :: Science/Research
Classifier: License :: OSI Approved :: MIT License
Classifier: Programming Language :: Python :: 3
Classifier: Topic :: Scientific/Engineering :: Astronomy
Requires-Python: >=3.8
Requires-Dist: corner>=2.2.0
Requires-Dist: jax>=0.4.0
Requires-Dist: jaxlib>=0.4.0
Requires-Dist: numpyro>=0.15.0
Requires-Dist: jax-cosmo>=0.1.0
Requires-Dist: numpy
Requires-Dist: scipy
Requires-Dist: matplotlib
Requires-Dist: astropy
Requires-Dist: photutils
Requires-Dist: arviz
Requires-Dist: xarray
Requires-Dist: scikit-image
Requires-Dist: reproject
Provides-Extra: dev
Requires-Dist: pytest; extra == "dev"
